euromsg/__init__.py
euromsg/euromsg.py
python_euromsg-0.0.1.dist-info/DESCRIPTION.rst
python_euromsg-0.0.1.dist-info/METADATA
python_euromsg-0.0.1.dist-info/RECORD
python_euromsg-0.0.1.dist-info/WHEEL
python_euromsg-0.0.1.dist-info/metadata.json
python_euromsg-0.0.1.dist-info/top_level.txt
python_euromsg-0.0.1.dist-info/zip-safe
