Metadata-Version: 2.0
Name: python-euromsg
Version: 0.0.1
Summary: Python utility for sending email over euro.message (https://www.euromsg.com) service 
Home-page: https://github.com/nazmizorlu/python-euromsg
Author: Nazmi ZORLU
Author-email: nazmizorlu@gmail.com
License: MIT
Keywords: euromsg euro.message
Platform: UNKNOWN
Classifier: Development Status :: 3 - Alpha
Classifier: Intended Audience :: Developers
Classifier: Topic :: Communications :: Email
Classifier: License :: OSI Approved :: MIT License
Classifier: Programming Language :: Python :: 2
Classifier: Programming Language :: Python :: 2.7
Classifier: Programming Language :: Python :: 3
Classifier: Programming Language :: Python :: 3.3
Classifier: Programming Language :: Python :: 3.4
Classifier: Programming Language :: Python :: 3.5
Classifier: Programming Language :: Python :: 3.6
Requires-Dist: zeep (>=1.3.0)
